{"cameraMode":{"drawMode":0,"name":"Shaded","section":"Shading Mode"},"sceneLighting":true,"audioPlay":false,"sceneViewState":{"showFog":true,"showMaterialUpdate":false,"showSkybox":true,"showFlares":true,"showImageEffects":true,"showParticleSystems":true},"in2DMode":false,"pivot":{"x":1.5208659172058106,"y":9.23956298828125,"z":2.5416088104248049},"rotation":{"x":-0.4575566053390503,"y":0.16804756224155427,"z":-0.08851736038923264,"w":-0.8686580061912537},"size":25.806659698486329,"orthographic":false}